[{"id": "f1d9a0bb-90f9-4085-a859-d797a1df42b1", "date": "2024-08-08", "time": "20:05:00", "type": "cabaret", "subtype": "drag", "title": "Reuben Kaye: Live and Intimidating", "venue_id": "3fa2ed56-10bb-4e0a-abc8-c3ddf8aca67f", "venue_name": "Palais du Variété, Assembly George Square Gardens", "festival_id": "f303bd11-9f8f-5710-97c8-b8853094ea21", "festival_name": "Edinburgh Festival Fringe 2024", "price_paid": "13.00", "currency": "GBP", "payment_method_id": null, "rating": null, "data_completeness": null, "status": "attended", "primary_entity_name": null, "primary_entity_id": null, "primary_entity_kind": null, "has_review": false, "has_essay": false}, {"id": "efed0c34-a023-4520-901f-131ffcc33876", "date": "2023-08-27", "time": "19:50:00", "type": "cabaret", "subtype": "drag", "title": "Reuben Kaye: The Butch is Back", "venue_id": "3fa2ed56-10bb-4e0a-abc8-c3ddf8aca67f", "venue_name": "Palais du Variété, Assembly George Square Gardens", "festival_id": "f3b89f18-57de-5997-89c9-beeb7d212930", "festival_name": "Edinburgh Festival Fringe 2023", "price_paid": "17.50", "currency": "GBP", "payment_method_id": null, "rating": null, "data_completeness": "complete", "status": "attended", "primary_entity_name": null, "primary_entity_id": null, "primary_entity_kind": null, "has_review": false, "has_essay": false}]