[{"id": "b01554ad-221b-5d6d-b478-2dd5cd7a53cb", "date": "2014-08-05", "time": "20:30:00", "type": "comedy", "subtype": "standup", "title": "Daniel Sloss: Really…?!", "venue_id": "2c075649-4908-50e2-8539-98ad77b013c2", "venue_name": "Lomond Theatre, EICC", "festival_id": "e389062a-846b-573a-89cf-1a6ec8d8c839", "festival_name": "Edinburgh Festival Fringe 2014", "price_paid": "9.65", "currency": "GBP", "payment_method_id": null, "rating": null, "data_completeness": "complete", "status": "attended", "primary_entity_name": null, "primary_entity_id": null, "primary_entity_kind": null, "has_review": false, "has_essay": false}]