[{"id": "242abfcc-81c2-4d07-a0ca-fdc6b767ff2f", "date": "2024-08-18", "time": "21:55:00", "type": "comedy", "subtype": "standup", "title": "Catherine Bohart: Again, With Feelings", "venue_id": "d55fd30b-1f48-479f-a6e0-79f18d503b94", "venue_name": "Monkey Barrel 3, Monkey Barrel Comedy", "festival_id": "f303bd11-9f8f-5710-97c8-b8853094ea21", "festival_name": "Edinburgh Festival Fringe 2024", "price_paid": "20.00", "currency": "GBP", "payment_method_id": null, "rating": 4.5, "rating_context": "intimate", "data_completeness": "complete", "primary_entity_name": null, "primary_entity_id": null, "primary_entity_kind": null, "has_review": false, "has_essay": false}, {"id": "25e28aae-d372-4f06-8a30-05558cb3e17f", "date": "2022-08-26", "time": "15:00:00", "type": "comedy", "subtype": "standup", "title": "Catherine Bohart: This Isn't For You", "venue_id": "d55fd30b-1f48-479f-a6e0-79f18d503b94", "venue_name": "Monkey Barrel 3, Monkey Barrel Comedy", "festival_id": "db0cec0e-8d92-4c67-b7b7-b5d5b80f017c", "festival_name": "Edinburgh Festival Fringe 2022", "price_paid": "12.00", "currency": "GBP", "payment_method_id": null, "rating": 4.0, "rating_context": "studio", "data_completeness": "partial", "primary_entity_name": null, "primary_entity_id": null, "primary_entity_kind": null, "has_review": false, "has_essay": false}]