[{"id": "de716222-f1c0-526f-8f4e-8bb474144c51", "date": "2026-05-08", "time": "12:30:00", "type": "classical", "subtype": "recital", "title": "Lunchconcert: Floor Kes, Alicia De Keulenaer + Katja Naegele", "venue_id": "13bfda8e-1e81-5a2c-8726-864fba58d287", "venue_name": "Grote Zaal, Muziekgebouw aan 't IJ", "festival_id": null, "festival_name": null, "price_paid": "6.50", "currency": "EUR", "payment_method_id": null, "rating": 4.0, "rating_context": "theatre", "data_completeness": "complete", "status": "attended", "primary_entity_name": null, "primary_entity_id": null, "primary_entity_kind": null, "has_review": false, "has_essay": false}, {"id": "f4697fde-0ebb-4d46-aad0-f71114d798ac", "date": "2026-05-02", "time": "14:00:00", "type": "ballet", "subtype": "mixed_bill", "title": "Hans van Manen in Carré", "venue_id": "e1fe87e4-9f2a-5f45-9f7c-f0ff922c9909", "venue_name": "Koninklijk Theater Carré", "festival_id": null, "festival_name": null, "price_paid": "19.52", "currency": "EUR", "payment_method_id": null, "rating": 4.5, "rating_context": "theatre", "data_completeness": "partial", "status": "attended", "primary_entity_name": null, "primary_entity_id": null, "primary_entity_kind": null, "has_review": false, "has_essay": true}]