{"id": "03846898-78a7-4810-8079-a86837acfa7a", "date": "2017-08-22", "time": "19:00:00", "type": "circus", "subtype": "contemporary", "title": "Circa: Humans", "venue": {"id": "90804099-9eb6-58ba-aca3-2058aa0be3bd", "name": "The Lafayette"}, "venue_path": [{"id": "43bd7e2f-edb6-5507-9a79-8b0da9d4f695", "name": "Underbelly's Circus Hub"}, {"id": "1382852e-76eb-54ca-a679-81e7e48ff1f9", "name": "The Meadows"}], "work_id": null, "festival": {"id": "3c5f5265-a8b9-4d57-a09e-7cca94eb6667", "name": "Edinburgh Festival Fringe 2017"}, "price_paid": "17.50", "currency": "GBP", "payment_method": null, "rating": 5.0, "rating_context": "theatre", "notes": null, "review": null, "links": null, "data_completeness": "complete", "related_events": [], "extension": {"subtype": null, "company": {"id": "9d0828af-0bab-5b20-99dc-32ff30684e7f", "name": "Circa"}, "director": null, "work": null}}