{"id": "0512f97d-bb4d-4124-b1e3-a1619eeb2ca5", "date": "2022-05-30", "time": null, "type": "exhibition", "subtype": "art", "title": "Straat Museum", "venue": {"id": "a9f87366-deda-4a22-8f30-0f84283098dc", "name": "Straat Museum"}, "venue_path": [], "work_id": null, "festival": null, "price_paid": null, "currency": null, "payment_method": null, "rating": null, "notes": null, "review": null, "links": null, "data_completeness": null, "status": "attended", "related_events": [], "extension": {"subtype": "art", "exhibition_title": null, "artists": null, "period": null, "medium": null, "curator": null, "permanent_or_temp": "permanent", "exhibition_url": null}}