{"id": "59535711-5627-42e6-9b20-77f690be4694", "date": "2025-08-24", "time": "12:15:00", "type": "theatre", "subtype": "play", "title": "FLUSH", "venue": {"id": "a1b2e0a8-27fb-4743-a2ae-29ed9bcb1273", "name": "Upstairs"}, "venue_path": [{"id": "4fac56c7-0d7d-4ce1-9cd5-934c65b50e5b", "name": "Pleasance Courtyard"}], "work_id": null, "festival": {"id": "e97226c4-aa75-5c9f-b3ca-fbe8769dae2a", "name": "Edinburgh Festival Fringe 2025"}, "price_paid": "14.00", "currency": "GBP", "payment_method": null, "rating": 5.0, "rating_context": "studio", "notes": null, "review": null, "links": null, "data_completeness": "complete", "full_description": "Three bathroom stalls in a Shoreditch nightclub. One night. Stories slip between the cracks of the cubicles: teenage drama, thirty-something fatigue, love, loss, career spirals, sex, motherhood, bad dates and worse decisions. At the heart of it all is Billie, who has just experienced something she can't quite name yet — and the bathroom becomes a strange kind of shelter. Winner of a Fringe Theatre Award, Bitesize Award for Best Direction, and one of the FT's top nine shows of the Fringe.", "ai_summary": "April Hope Miller's debut play — a warm, funny, and occasionally devastating ensemble piece set entirely in a nightclub bathroom — won a Fringe Theatre Award and a Bitesize Award for Best Direction. One of the most talked-about new plays of Fringe 2025.", "description_source_url": "https://www.arcolatheatre.com/event/flush/", "related_events": [], "extension": {"subtype": null, "work": null, "company": null, "director": null, "playwright": null, "cast": null, "credits": null}}