[{"id": "834e4c50-75ec-5bc1-ae89-393e157ec4a4", "date": "2026-06-14", "time": "16:00:00", "type": "dance", "subtype": "hip_hop", "title": "Oxygen: The Rise", "venue_id": "c5873a4c-1a59-583e-8724-493ea28ba77e", "venue_name": "Wim Sonneveld zaal, DeLaMar", "festival_id": null, "festival_name": null, "price_paid": "31.00", "currency": "EUR", "payment_method_id": null, "rating": 2.0, "rating_context": "theatre", "data_completeness": "complete", "primary_entity_name": null, "primary_entity_id": null, "primary_entity_kind": null, "has_review": true, "has_essay": false}, {"id": "040f9371-d922-4f63-b27b-2e1fe6f5d12b", "date": "2025-10-25", "time": "20:00:00", "type": "circus", "subtype": "contemporary", "title": "YOAH", "venue_id": "73bda974-ce06-568d-a1e8-04c85478f6f4", "venue_name": "DeLaMar", "festival_id": null, "festival_name": null, "price_paid": "55.00", "currency": "EUR", "payment_method_id": null, "rating": 4.0, "rating_context": "theatre", "data_completeness": null, "primary_entity_name": null, "primary_entity_id": null, "primary_entity_kind": null, "has_review": false, "has_essay": false}, {"id": "fa9955c5-8e3b-4c99-83b8-8be682e871f8", "date": "2022-10-09", "time": null, "type": "comedy", "subtype": "standup", "title": "Alan Carr: Not Again Alan!", "venue_id": "73bda974-ce06-568d-a1e8-04c85478f6f4", "venue_name": "DeLaMar", "festival_id": null, "festival_name": null, "price_paid": "15.00", "currency": "EUR", "payment_method_id": null, "rating": 3.5, "rating_context": "theatre", "data_completeness": null, "primary_entity_name": null, "primary_entity_id": null, "primary_entity_kind": null, "has_review": true, "has_essay": false}]